cqu/README.md
cqu/__init__.py
cqu/__logging/__init__.py
cqu/__logging/__logger.py
cqu/classical_models/__init__.py
cqu/classical_models/important_features.py
cqu/classical_models/main.py
cqu/classical_models/models.py
cqu/classical_models/plotter.py
cqu/preprocessing/__init__.py
cqu/preprocessing/missing_values.py
cqu/preprocessing/preprocessor.py
cqu/preprocessing/smote.py
cqu/preprocessing/standardization.py
cqu/preprocessing/type_conversion.py
cqu/quantum_embedding/__init__.py
cqu/quantum_embedding/quantum_classifier.py
cqu-0.1.1.dist-info/METADATA
cqu-0.1.1.dist-info/WHEEL
cqu-0.1.1.dist-info/top_level.txt
cqu-0.1.1.dist-info/RECORD
